rlextra/__init__.py
rlextra/main.py
rlextra/py.typed
rlextra-0.0.1.dist-info/METADATA
rlextra-0.0.1.dist-info/WHEEL
rlextra-0.0.1.dist-info/top_level.txt
rlextra-0.0.1.dist-info/RECORD
